conversational_markov-0.1.4.dist-info/licenses/LICENSE
convmark/__init__.py
conversational_markov-0.1.4.dist-info/METADATA
conversational_markov-0.1.4.dist-info/WHEEL
conversational_markov-0.1.4.dist-info/top_level.txt
conversational_markov-0.1.4.dist-info/RECORD
