Metadata-Version: 2.4
Name: conversational-markov
Version: 0.1.4
Summary: Markov chain generator with rudimentary prompt response
Project-URL: Homepage, https://github.com/garlic-os/conversational-markov
Requires-Python: >=3.13
License-File: LICENSE
Requires-Dist: markovify
Dynamic: license-file
